LICENSE
README.md
pyproject.toml
setup.py
robustica/InferComponents.py
robustica/RobustICA.py
robustica/__init__.py
robustica/examples.py
robustica.egg-info/PKG-INFO
robustica.egg-info/SOURCES.txt
robustica.egg-info/dependency_links.txt
robustica.egg-info/requires.txt
robustica.egg-info/top_level.txt