Metadata-Version: 2.1
Name: robustica
Version: 0.1.4
Summary: Fully cumstomizable robust Independent Components Analysis (ICA)
Home-page: https://github.com/CRG-CNAG/robustica
Author: Miquel Anglada Girotto
Author-email: miquel.anglada@crg.eu
Project-URL: Issues, https://github.com/CRG-CNAG/robustica/issues
Project-URL: Documentation, https://crg-cnag.github.io/robustica/
Requires-Python: >=3.8
License-File: LICENSE
Requires-Dist: numpy
Requires-Dist: pandas
Requires-Dist: scipy
Requires-Dist: scikit-learn
Requires-Dist: joblib
Requires-Dist: tqdm
Provides-Extra: extra
Requires-Dist: scikit-learn-extra; extra == "extra"
